napari_cursor_tracker/__init__.py
napari_cursor_tracker/_sample_data.py
napari_cursor_tracker/_version.py
napari_cursor_tracker/_widget.py
napari_cursor_tracker/napari.yaml
napari_cursor_tracker/_tests/__init__.py
napari_cursor_tracker/_tests/test_sample_data.py
napari_cursor_tracker/_tests/test_widget.py
napari_cursor_tracker-0.1.3.dist-info/LICENSE
napari_cursor_tracker-0.1.3.dist-info/METADATA
napari_cursor_tracker-0.1.3.dist-info/WHEEL
napari_cursor_tracker-0.1.3.dist-info/entry_points.txt
napari_cursor_tracker-0.1.3.dist-info/top_level.txt
napari_cursor_tracker-0.1.3.dist-info/RECORD
